tartaro/__init__.py
tartaro/equidna.py
rpgfactory-0.0.1.dist-info/METADATA
rpgfactory-0.0.1.dist-info/WHEEL
rpgfactory-0.0.1.dist-info/top_level.txt
rpgfactory-0.0.1.dist-info/RECORD
